<annotation>
    <folder>train</folder>
    <filename>character_family_003.jpg</filename>
    <size>
        <width>4032</width>
        <height>3024</height>
        <depth>3</depth>
    </size>
    <object>
        <name>character-nine</name>
        <pose>Unspecified</pose>
        <truncated>0</truncated>
        <occluded>0</occluded>
        <difficult>0</difficult>
        <polygon>
            <x1>2961.838342</x1>
            <y1>2191.519512</y1>
            <x2>3198.145742</x2>
            <y2>2554.853052</y2>
            <x3>2737.797236</x3>
            <y3>2841.985279</y3>
            <x4>2529.096248</x4>
            <y4>2467.734771</y4>
        </polygon>
        <bndbox>
            <xmin>2529.096191</xmin>
            <ymin>2191.519531</ymin>
            <xmax>3198.145752</xmax>
            <ymax>2841.985352</ymax>
        </bndbox>
    </object>
    <object>
        <name>character-eight</name>
        <pose>Unspecified</pose>
        <truncated>0</truncated>
        <occluded>0</occluded>
        <difficult>0</difficult>
        <polygon>
            <x1>1781.084299</x1>
            <y1>2092.491152</y1>
            <x2>2166.696856</x2>
            <y2>1998.377602</y2>
            <x3>2297.624320</x3>
            <y3>2535.215556</y3>
            <x4>1898.041818</x4>
            <y4>2639.049992</y4>
        </polygon>
        <bndbox>
            <xmin>1781.084351</xmin>
            <ymin>1998.377563</ymin>
            <xmax>2297.624268</xmax>
            <ymax>2639.050049</ymax>
        </bndbox>
    </object>
    <object>
        <name>character-seven</name>
        <pose>Unspecified</pose>
        <truncated>0</truncated>
        <occluded>0</occluded>
        <difficult>0</difficult>
        <polygon>
            <x1>777.495560</x1>
            <y1>2420.971580</y1>
            <x2>1128.273871</x2>
            <y2>2198.638014</y2>
            <x3>1403.083805</x3>
            <y3>2664.856373</y3>
            <x4>1042.003836</x4>
            <y4>2908.951386</y4>
        </polygon>
        <bndbox>
            <xmin>777.495544</xmin>
            <ymin>2198.637939</ymin>
            <xmax>1403.083862</xmax>
            <ymax>2908.951416</ymax>
        </bndbox>
    </object>
    <object>
        <name>character-six</name>
        <pose>Unspecified</pose>
        <truncated>0</truncated>
        <occluded>0</occluded>
        <difficult>0</difficult>
        <polygon>
            <x1>2692.045120</x1>
            <y1>1127.774711</y1>
            <x2>3032.239040</x2>
            <y2>1304.352694</y2>
            <x3>2809.046136</x3>
            <y3>1737.812898</y3>
            <x4>2463.560020</x4>
            <y4>1551.441538</y4>
        </polygon>
        <bndbox>
            <xmin>2463.560059</xmin>
            <ymin>1127.774658</ymin>
            <xmax>3032.239014</xmax>
            <ymax>1737.812866</ymax>
        </bndbox>
    </object>
    <object>
        <name>character-five</name>
        <pose>Unspecified</pose>
        <truncated>0</truncated>
        <occluded>0</occluded>
        <difficult>0</difficult>
        <polygon>
            <x1>1656.036246</x1>
            <y1>1259.916427</y1>
            <x2>1987.893146</x2>
            <y2>1105.397099</y2>
            <x3>2208.432704</x3>
            <y3>1533.667031</y3>
            <x4>1867.426830</x4>
            <y4>1694.007292</y4>
        </polygon>
        <bndbox>
            <xmin>1656.036255</xmin>
            <ymin>1105.397095</ymin>
            <xmax>2208.432617</xmax>
            <ymax>1694.007324</ymax>
        </bndbox>
    </object>
    <object>
        <name>character-four</name>
        <pose>Unspecified</pose>
        <truncated>0</truncated>
        <occluded>0</occluded>
        <difficult>0</difficult>
        <polygon>
            <x1>952.594732</x1>
            <y1>1281.938838</y1>
            <x2>1338.620515</x2>
            <y2>1286.933388</y2>
            <x3>1307.382063</x3>
            <y3>1785.743175</y3>
            <x4>913.765967</x4>
            <y4>1777.218371</y4>
        </polygon>
        <bndbox>
            <xmin>913.765991</xmin>
            <ymin>1281.938843</ymin>
            <xmax>1338.620483</xmax>
            <ymax>1785.743164</ymax>
        </bndbox>
    </object>
    <object>
        <name>character-three</name>
        <pose>Unspecified</pose>
        <truncated>0</truncated>
        <occluded>0</occluded>
        <difficult>0</difficult>
        <polygon>
            <x1>2633.328102</x1>
            <y1>339.664519</y1>
            <x2>2975.178888</x2>
            <y2>464.580831</y2>
            <x3>2822.775339</x3>
            <y3>866.837956</y3>
            <x4>2476.465907</x4>
            <y4>739.749017</y4>
        </polygon>
        <bndbox>
            <xmin>2476.465820</xmin>
            <ymin>339.664520</ymin>
            <xmax>2975.178955</xmax>
            <ymax>866.837952</ymax>
        </bndbox>
    </object>
    <object>
        <name>character-two</name>
        <pose>Unspecified</pose>
        <truncated>0</truncated>
        <occluded>0</occluded>
        <difficult>0</difficult>
        <polygon>
            <x1>1863.364678</x1>
            <y1>219.409249</y1>
            <x2>2182.176291</x2>
            <y2>357.801421</y2>
            <x3>1977.256764</x3>
            <y3>746.343470</y3>
            <x4>1657.611298</x4>
            <y4>595.086420</y4>
        </polygon>
        <bndbox>
            <xmin>1657.611328</xmin>
            <ymin>219.409256</ymin>
            <xmax>2182.176270</xmax>
            <ymax>746.343445</ymax>
        </bndbox>
    </object>
    <object>
        <name>character-one</name>
        <pose>Unspecified</pose>
        <truncated>0</truncated>
        <occluded>0</occluded>
        <difficult>0</difficult>
        <polygon>
            <x1>908.184101</x1>
            <y1>435.582822</y1>
            <x2>1236.800540</x2>
            <y2>287.287260</y2>
            <x3>1436.423955</x3>
            <y3>661.984848</y3>
            <x4>1096.733270</x4>
            <y4>820.879717</y4>
        </polygon>
        <bndbox>
            <xmin>908.184082</xmin>
            <ymin>287.287262</ymin>
            <xmax>1436.423950</xmax>
            <ymax>820.879700</ymax>
        </bndbox>
    </object>
</annotation>